{
  "নাম": "ওগো তোমরা যত পাড়ার মেয়ে",
  "পর্যায়": "চণ্ডালিকা (গীতবিতান)",
  "রাগ": "ভৈরবী",
  "তাল": "কাহারবা",
  "রচনাকাল (বঙ্গাব্দ)": "1344",
  "রচনাকাল (খৃষ্টাব্দ)": "1938",
  "স্বরলিপিকার": "শৈলজারঞ্জন মজুমদার",
  "কথা": [
    "  ওগো      তোমরা যত পাড়ার মেয়ে,",
    "                          এসো এসো দেখো চেয়ে,",
    "                             এনেছি কাঁকনজোড়া",
    "                             সোনালি তারে মোড়া।",
    "                         আমার কথা শোনো,",
    "                               হাতে লহ প'রে,",
    "                             যারে রাখিতে চাহ ধ'রে",
    "                             কাঁকন দুটি বেড়ি হয়ে",
    "                                   বাঁধিবে মন তাহার--",
    "                                      আমি দিলাম কয়ে॥"
  ]
}
