{
  "নাম": "দিন অবসান হল",
  "পর্যায়": "পূজা",
  "রাগ": "ইমন-পূরবী",
  "তাল": "কাহারবা",
  "রচনাকাল (বঙ্গাব্দ)": "1328",
  "রচনাকাল (খৃষ্টাব্দ)": "1921",
  "রচনাস্থান": "শান্তিনিকেতন",
  "স্বরলিপিকার": "দিনেন্দ্রনাথ ঠাকুর",
  "কথা": [
    "                   দিন অবসান হল।",
    "আমার  আঁখি হতে অস্তরবির আলোর আড়াল তোলো ॥",
    "অন্ধকারের বুকের কাছে   নিত্য-আলোর আসন আছে,",
    "              সেথায় তোমার দুয়ারখানি খোলো ॥",
    "সব কথা সব কথার শেষে   এক হয়ে যাক মিলিয়ে এসে।",
    "স্তব্ধ বাণীর হৃদয় মাঝে   গভীর বাণী আপনি বাজে,",
    "              সেই বাণীটি আমার কানে বোলো ॥"
  ]
}
